[{"name":"N2fYY0","marks":37},{"name":"jLG6s","marks":84},{"name":"S","marks":86},{"name":"ImUXshouD","marks":65},{"name":"VVzLhvY","marks":38},{"name":"yoNC8MuDTW","marks":70},{"name":"KoAH","marks":89},{"name":"6eKT6nnZM","marks":28},{"name":"GB5n9m","marks":42},{"name":"aEPqveiRs","marks":35},{"name":"U1MYAe","marks":89},{"name":"U7cH","marks":14},{"name":"8","marks":91},{"name":"a3c","marks":71},{"name":"p","marks":41},{"name":"gM8Tj","marks":31},{"name":"VY3T0HCB","marks":87},{"name":"5vhSbh9","marks":52},{"name":"fMMo0kPr","marks":45},{"name":"XYAs","marks":62},{"name":"M","marks":79},{"name":"hI","marks":72},{"name":"EQK","marks":67},{"name":"G1DIlJFi","marks":78},{"name":"87vWqL8WFI","marks":66},{"name":"O","marks":64},{"name":"jN0","marks":29},{"name":"g80","marks":53},{"name":"0T","marks":6},{"name":"M","marks":74},{"name":"kFDQRxcAN","marks":42},{"name":"zMxSH8Yq","marks":94},{"name":"2","marks":34},{"name":"6SQePmf","marks":47},{"name":"En","marks":12},{"name":"mF","marks":65},{"name":"80KEus3zy2","marks":38},{"name":"X8pDvZeR","marks":60},{"name":"bGS2","marks":32},{"name":"OeyM","marks":71},{"name":"9fgd","marks":19},{"name":"55Z","marks":30},{"name":"xqK","marks":59},{"name":"J","marks":89},{"name":"8S","marks":25},{"name":"D3e4tXnqD","marks":72},{"name":"W","marks":32},{"name":"S0Cr9YP","marks":95},{"name":"dLJGOJ","marks":73},{"name":"GtFEP","marks":93},{"name":"0t","marks":55},{"name":"IzT0Y","marks":18},{"name":"KYSQ","marks":32},{"name":"cKGwtvr","marks":69},{"name":"danzc8WF","marks":55},{"name":"SPc7t","marks":5},{"name":"50JeTC4","marks":72},{"name":"MQM","marks":27},{"name":"C8VeWUtQ","marks":2},{"name":"DPilJ","marks":19},{"name":"9VqwgV","marks":94},{"name":"WCu","marks":83},{"name":"FS03KOBZ","marks":99},{"name":"vJFDo7xC6W","marks":0},{"name":"lHTvkA0x","marks":52},{"name":"QkOGNG5w","marks":55},{"name":"0dd3glQS5d","marks":25},{"name":"Me9S03gXF8","marks":58},{"name":"BMOtiC","marks":76},{"name":"SOb0vTvln9","marks":95},{"name":"kSXB","marks":5},{"name":"cuYbpe","marks":34},{"name":"tKSWrxE2p","marks":0},{"name":"aPJpSDk","marks":32},{"name":"sq9wYs","marks":69},{"name":"T12VMewz","marks":73},{"name":"Q6SRC","marks":55},{"name":"vf1enG","marks":88},{"name":"eVQ5diRf1","marks":85},{"name":"NPVgIbz","marks":46},{"name":"y0","marks":36},{"name":"HoJO7OL5cs","marks":37},{"name":"1tX","marks":16},{"name":"7lnkEV","marks":59},{"name":"7Www45Jge","marks":60},{"name":"Do3","marks":50},{"name":"iFivOAk","marks":37},{"name":"joY5h2","marks":63},{"name":"Zu7AER5k","marks":54},{"name":"BxvqggYSEC","marks":24},{"name":"qfHMygi","marks":22},{"name":"KqE","marks":52},{"name":"w8cKep","marks":78},{"name":"TANeHzNQIX","marks":99},{"name":"x7GBw7","marks":91},{"name":"9kVOpQ","marks":69},{"name":"agwmJsXd","marks":58},{"name":"KsrX083","marks":17},{"name":"fczvO1","marks":28},{"name":"DWMN","marks":8}]